{
  "tabletypeflag": "S",
  "parenttablename": "",
  "inactive": false,
  "iseditable": true,
  "level": 1,
  "issystemtable": false,
  "tabletype": "משטח חיפוש",
  "title": "Mobile Recent Customer Receipts",
  "tablename": "LastReceipts",
  "primarykey": "LastReceipts",
  "ngv_modifydate": "2025-07-01T11:49:21.08964",
  "ngv_hashcode": "",
  "noskip": null,
  "priformname": null,
  "enforcebpm": null,
  "chk": null,
  "curlangtitle": "קבלות אחרונות ללקוח (נייד)",
  "istrackchanges": null,
  "testadd": null,
  "SysTableConds": [],
  "SysTableFromEnts": [],
  "SysTablesConts": [],
  "SysServerIndexes": [],
  "SysTableOrgConds": [],
  "SysTableColumns": [
    {
      "name": "AvgDate",
      "title": "Invoice Date (Avg)",
      "isboolean": false,
      "isicon": false,
      "isid": false,
      "latitude": false,
      "longitude": false,
      "colorder": 8,
      "primarykey": "LastReceipts:AvgDate",
      "fatherkey": "LastReceipts",
      "ngv_modifydate": "2025-06-24T06:20:01.012898",
      "ngv_hashcode": "",
      "isurl": null,
      "isfiledesc": null,
      "currentlangtitle": "ת. חשבוניות משוקלל",
      "type": "Str",
      "iseditable": true,
      "maxwidth": 16,
      "transferchanges": true,
      "SysTableColumnQuery": []
    },
    {
      "name": "CustomerName",
      "title": "Customer Name",
      "isboolean": false,
      "isicon": false,
      "isid": false,
      "latitude": false,
      "longitude": false,
      "colorder": 2,
      "primarykey": "LastReceipts:CustomerName",
      "fatherkey": "LastReceipts",
      "ngv_modifydate": "2025-06-24T06:20:01.012898",
      "ngv_hashcode": "",
      "isurl": null,
      "isfiledesc": null,
      "currentlangtitle": "שם לקוח",
      "type": "Str",
      "iseditable": true,
      "maxwidth": 48,
      "transferchanges": true,
      "SysTableColumnQuery": []
    },
    {
      "name": "CustomerNo",
      "title": "Customer No",
      "isboolean": false,
      "isicon": false,
      "isid": false,
      "latitude": false,
      "longitude": false,
      "colorder": 1,
      "primarykey": "LastReceipts:CustomerNo",
      "fatherkey": "LastReceipts",
      "ngv_modifydate": "2025-06-24T06:20:01.012898",
      "ngv_hashcode": "",
      "isurl": null,
      "isfiledesc": null,
      "currentlangtitle": "מס. לקוח",
      "type": "Str",
      "iseditable": true,
      "maxwidth": 16,
      "transferchanges": true,
      "SysTableColumnQuery": []
    },
    {
      "name": "InvoiceNo",
      "title": "Invoice No",
      "isboolean": false,
      "isicon": false,
      "isid": false,
      "latitude": false,
      "longitude": false,
      "colorder": 4,
      "primarykey": "LastReceipts:InvoiceNo",
      "fatherkey": "LastReceipts",
      "ngv_modifydate": "2025-06-24T06:20:01.012898",
      "ngv_hashcode": "",
      "isurl": null,
      "isfiledesc": null,
      "currentlangtitle": "חשבונית",
      "type": "Str",
      "iseditable": true,
      "maxwidth": 16,
      "transferchanges": true,
      "SysTableColumnQuery": []
    },
    {
      "name": "Month",
      "title": "Month",
      "isboolean": false,
      "isicon": false,
      "isid": false,
      "latitude": false,
      "longitude": false,
      "colorder": 6,
      "primarykey": "LastReceipts:Month",
      "fatherkey": "LastReceipts",
      "ngv_modifydate": "2025-06-24T06:20:01.012898",
      "ngv_hashcode": "",
      "isurl": null,
      "isfiledesc": null,
      "currentlangtitle": "חודש תאריך",
      "type": "Str",
      "iseditable": true,
      "maxwidth": 10,
      "transferchanges": true,
      "SysTableColumnQuery": []
    },
    {
      "name": "Date",
      "title": "Date",
      "isboolean": false,
      "isicon": false,
      "isid": false,
      "latitude": false,
      "longitude": false,
      "colorder": 3,
      "primarykey": "LastReceipts:Date",
      "fatherkey": "LastReceipts",
      "ngv_modifydate": "2025-06-24T06:20:01.012898",
      "ngv_hashcode": "",
      "isurl": null,
      "isfiledesc": null,
      "currentlangtitle": "תאריך",
      "type": "Date",
      "iseditable": true,
      "maxwidth": 8,
      "transferchanges": true,
      "SysTableColumnQuery": []
    },
    {
      "name": "PayDate",
      "title": "Payment Date",
      "isboolean": false,
      "isicon": false,
      "isid": false,
      "latitude": false,
      "longitude": false,
      "colorder": 7,
      "primarykey": "LastReceipts:PayDate",
      "fatherkey": "LastReceipts",
      "ngv_modifydate": "2025-06-24T06:20:01.012898",
      "ngv_hashcode": "",
      "isurl": null,
      "isfiledesc": null,
      "currentlangtitle": "ת. תשלום משוקלל",
      "type": "Date",
      "iseditable": true,
      "maxwidth": 8,
      "transferchanges": true,
      "SysTableColumnQuery": []
    },
    {
      "name": "TotalReceipts",
      "title": "Total Receipts",
      "isboolean": false,
      "isicon": false,
      "isid": false,
      "latitude": false,
      "longitude": false,
      "colorder": 5,
      "primarykey": "LastReceipts:TotalReceipts",
      "fatherkey": "LastReceipts",
      "ngv_modifydate": "2025-06-24T06:20:01.012898",
      "ngv_hashcode": "",
      "isurl": null,
      "isfiledesc": null,
      "currentlangtitle": "סה\"כ תקבולים",
      "type": "Float",
      "iseditable": true,
      "maxwidth": 16,
      "transferchanges": true,
      "SysTableColumnQuery": []
    }
  ],
  "SysPermissionDependencies": []
}
