{
  "tabletypeflag": "Y",
  "parenttablename": "",
  "inactive": false,
  "iseditable": true,
  "level": 1,
  "issystemtable": false,
  "tabletype": "מחוללים-קוד",
  "title": "Mobile Command Types",
  "tablename": "SysCmdTypes",
  "primarykey": "SysCmdTypes",
  "ngv_modifydate": "2025-06-30T09:34:54.817892",
  "ngv_hashcode": "",
  "noskip": null,
  "priformname": null,
  "enforcebpm": null,
  "chk": null,
  "curlangtitle": "סוגי פקודות (נייד)",
  "istrackchanges": null,
  "testadd": null,
  "SysTableConds": [],
  "SysTableFromEnts": [],
  "SysTablesConts": [],
  "SysServerIndexes": [],
  "SysTableOrgConds": [],
  "SysTableColumns": [
    {
      "name": "CommandType",
      "title": "",
      "isboolean": false,
      "isicon": false,
      "isid": false,
      "latitude": false,
      "longitude": false,
      "colorder": 1,
      "primarykey": "SysCmdTypes:CommandType",
      "fatherkey": "SysCmdTypes",
      "ngv_modifydate": "2025-06-24T07:04:18.061967",
      "ngv_hashcode": "",
      "isurl": null,
      "isfiledesc": null,
      "currentlangtitle": "סוג פקודה",
      "type": "Str",
      "iseditable": true,
      "maxwidth": 12,
      "transferchanges": true,
      "SysTableColumnQuery": []
    },
    {
      "name": "EntType",
      "title": "",
      "isboolean": false,
      "isicon": false,
      "isid": false,
      "latitude": false,
      "longitude": false,
      "colorder": 3,
      "primarykey": "SysCmdTypes:EntType",
      "fatherkey": "SysCmdTypes",
      "ngv_modifydate": "2025-06-24T07:04:18.061967",
      "ngv_hashcode": "",
      "isurl": null,
      "isfiledesc": null,
      "currentlangtitle": "סוג ישות מקושרת",
      "type": "Str",
      "iseditable": true,
      "maxwidth": 1,
      "transferchanges": true,
      "SysTableColumnQuery": []
    },
    {
      "name": "CommandTypeId",
      "title": "",
      "isboolean": false,
      "isicon": false,
      "isid": false,
      "latitude": false,
      "longitude": false,
      "colorder": 2,
      "primarykey": "SysCmdTypes:CommandTypeId",
      "fatherkey": "SysCmdTypes",
      "ngv_modifydate": "2025-06-24T07:04:18.061967",
      "ngv_hashcode": "",
      "isurl": null,
      "isfiledesc": null,
      "currentlangtitle": "סוג פקודה (ID)",
      "type": "Int",
      "iseditable": true,
      "maxwidth": 3,
      "transferchanges": true,
      "SysTableColumnQuery": []
    }
  ],
  "SysPermissionDependencies": []
}
WWW