{
  "tabletypeflag": "",
  "parenttablename": null,
  "inactive": null,
  "iseditable": true,
  "level": 1,
  "issystemtable": null,
  "tabletype": "טבלה רגילה",
  "title": "קבועי מערכת",
  "tablename": "SysConsts",
  "primarykey": "SysConsts",
  "ngv_modifydate": "2025-06-24T07:04:21.683167",
  "ngv_hashcode": "",
  "noskip": null,
  "priformname": null,
  "enforcebpm": null,
  "chk": null,
  "curlangtitle": null,
  "istrackchanges": null,
  "testadd": null,
  "SysTableConds": [],
  "SysTableFromEnts": [],
  "SysTablesConts": [],
  "SysServerIndexes": [],
  "SysTableOrgConds": [],
  "SysTableColumns": [
    {
      "name": "Value",
      "title": "Value",
      "isboolean": null,
      "isicon": false,
      "isid": false,
      "latitude": false,
      "longitude": false,
      "colorder": null,
      "primarykey": "SysConsts:Value",
      "fatherkey": "SysConsts",
      "ngv_modifydate": "2025-06-24T07:04:18.061967",
      "ngv_hashcode": "",
      "isurl": null,
      "isfiledesc": null,
      "currentlangtitle": "ערך",
      "type": "Str",
      "iseditable": true,
      "maxwidth": null,
      "transferchanges": true,
      "SysTableColumnQuery": []
    },
    {
      "name": "ConstDesc",
      "title": "Const Description",
      "isboolean": null,
      "isicon": false,
      "isid": false,
      "latitude": false,
      "longitude": false,
      "colorder": null,
      "primarykey": "SysConsts:ConstDesc",
      "fatherkey": "SysConsts",
      "ngv_modifydate": "2025-06-24T07:04:18.061967",
      "ngv_hashcode": "",
      "isurl": null,
      "isfiledesc": null,
      "currentlangtitle": "תאור קבוע",
      "type": "Str",
      "iseditable": true,
      "maxwidth": null,
      "transferchanges": true,
      "SysTableColumnQuery": []
    },
    {
      "name": "Const",
      "title": "Const Name",
      "isboolean": null,
      "isicon": false,
      "isid": false,
      "latitude": false,
      "longitude": false,
      "colorder": null,
      "primarykey": "SysConsts:Const",
      "fatherkey": "SysConsts",
      "ngv_modifydate": "2025-06-24T07:04:18.061967",
      "ngv_hashcode": "",
      "isurl": null,
      "isfiledesc": null,
      "currentlangtitle": "שם קבוע",
      "type": "Str",
      "iseditable": true,
      "maxwidth": null,
      "transferchanges": true,
      "SysTableColumnQuery": []
    }
  ],
  "SysPermissionDependencies": []
}
QQQ