{
  "tabletypeflag": "",
  "parenttablename": "SysCommands",
  "inactive": null,
  "iseditable": true,
  "level": 2,
  "issystemtable": true,
  "tabletype": "טבלת מערכת",
  "title": "Command Condition Items",
  "tablename": "SysCommandCondItems",
  "primarykey": "SysCommandCondItems",
  "ngv_modifydate": "2025-06-24T07:04:19.917639",
  "ngv_hashcode": "",
  "noskip": null,
  "priformname": null,
  "enforcebpm": null,
  "chk": null,
  "curlangtitle": "Command Condition Items",
  "istrackchanges": null,
  "testadd": null,
  "SysTableConds": [],
  "SysTableFromEnts": [],
  "SysTablesConts": [],
  "SysServerIndexes": [],
  "SysTableOrgConds": [],
  "SysTableColumns": [
    {
      "name": "ColumnName",
      "title": "Column Name",
      "isboolean": null,
      "isicon": false,
      "isid": false,
      "latitude": false,
      "longitude": false,
      "colorder": null,
      "primarykey": "SysCommandCondItems:ColumnName",
      "fatherkey": "SysCommandCondItems",
      "ngv_modifydate": "2025-06-24T07:04:18.061967",
      "ngv_hashcode": "",
      "isurl": null,
      "isfiledesc": null,
      "currentlangtitle": "שם עמודה",
      "type": "Str",
      "iseditable": true,
      "maxwidth": null,
      "transferchanges": true,
      "SysTableColumnQuery": []
    },
    {
      "name": "CommandName",
      "title": "Command Name",
      "isboolean": null,
      "isicon": false,
      "isid": false,
      "latitude": false,
      "longitude": false,
      "colorder": null,
      "primarykey": "SysCommandCondItems:CommandName",
      "fatherkey": "SysCommandCondItems",
      "ngv_modifydate": "2025-06-24T07:04:18.061967",
      "ngv_hashcode": "",
      "isurl": null,
      "isfiledesc": null,
      "currentlangtitle": "שם פקודה",
      "type": "Str",
      "iseditable": true,
      "maxwidth": null,
      "transferchanges": true,
      "SysTableColumnQuery": []
    },
    {
      "name": "Expr",
      "title": "Expression",
      "isboolean": null,
      "isicon": false,
      "isid": false,
      "latitude": false,
      "longitude": false,
      "colorder": null,
      "primarykey": "SysCommandCondItems:Expr",
      "fatherkey": "SysCommandCondItems",
      "ngv_modifydate": "2025-06-24T07:04:18.061967",
      "ngv_hashcode": "",
      "isurl": null,
      "isfiledesc": null,
      "currentlangtitle": "ביטוי",
      "type": "Str",
      "iseditable": true,
      "maxwidth": null,
      "transferchanges": true,
      "SysTableColumnQuery": []
    }
  ],
  "SysPermissionDependencies": []
}
GGGD