{
  "tabletypeflag": "",
  "parenttablename": "SysPageConditions",
  "inactive": false,
  "iseditable": true,
  "level": 3,
  "issystemtable": true,
  "tabletype": "טבלת מערכת",
  "title": "Page  Cond  Items",
  "tablename": "SysPageCondItems",
  "primarykey": "SysPageCondItems",
  "ngv_modifydate": "2025-06-24T07:05:11.404183",
  "ngv_hashcode": "",
  "noskip": null,
  "priformname": null,
  "enforcebpm": null,
  "chk": null,
  "curlangtitle": "תנאים לעיצוב",
  "istrackchanges": null,
  "testadd": null,
  "SysTableConds": [],
  "SysTableFromEnts": [],
  "SysTablesConts": [],
  "SysServerIndexes": [],
  "SysTableOrgConds": [],
  "SysTableColumns": [
    {
      "name": "ColumnName",
      "title": "Column Name",
      "isboolean": null,
      "isicon": false,
      "isid": null,
      "latitude": null,
      "longitude": null,
      "colorder": null,
      "primarykey": "SysPageCondItems:ColumnName",
      "fatherkey": "SysPageCondItems",
      "ngv_modifydate": "2025-06-24T07:04:18.061967",
      "ngv_hashcode": "",
      "isurl": null,
      "isfiledesc": null,
      "currentlangtitle": "שם עמודה",
      "type": "Str",
      "iseditable": true,
      "maxwidth": null,
      "transferchanges": true,
      "SysTableColumnQuery": []
    },
    {
      "name": "ConditionName",
      "title": "Condition Name",
      "isboolean": null,
      "isicon": false,
      "isid": null,
      "latitude": null,
      "longitude": null,
      "colorder": null,
      "primarykey": "SysPageCondItems:ConditionName",
      "fatherkey": "SysPageCondItems",
      "ngv_modifydate": "2025-06-24T07:04:18.061967",
      "ngv_hashcode": "",
      "isurl": null,
      "isfiledesc": null,
      "currentlangtitle": "שם תנאי",
      "type": "Str",
      "iseditable": true,
      "maxwidth": null,
      "transferchanges": true,
      "SysTableColumnQuery": []
    },
    {
      "name": "Expr",
      "title": "Expression",
      "isboolean": null,
      "isicon": false,
      "isid": null,
      "latitude": null,
      "longitude": null,
      "colorder": null,
      "primarykey": "SysPageCondItems:Expr",
      "fatherkey": "SysPageCondItems",
      "ngv_modifydate": "2025-06-24T07:04:18.061967",
      "ngv_hashcode": "",
      "isurl": null,
      "isfiledesc": null,
      "currentlangtitle": "ביטוי",
      "type": "Str",
      "iseditable": true,
      "maxwidth": null,
      "transferchanges": true,
      "SysTableColumnQuery": []
    },
    {
      "name": "PageName",
      "title": "Page Name",
      "isboolean": null,
      "isicon": false,
      "isid": null,
      "latitude": null,
      "longitude": null,
      "colorder": null,
      "primarykey": "SysPageCondItems:PageName",
      "fatherkey": "SysPageCondItems",
      "ngv_modifydate": "2025-06-24T07:04:18.061967",
      "ngv_hashcode": "",
      "isurl": null,
      "isfiledesc": null,
      "currentlangtitle": "שם דף",
      "type": "Str",
      "iseditable": true,
      "maxwidth": null,
      "transferchanges": true,
      "SysTableColumnQuery": []
    }
  ],
  "SysPermissionDependencies": []
}
QQQ